gradient_sdk/__init__.py
gradient_sdk/exceptions.py
gradient_sdk/hyper_parameter.py
gradient_sdk/multi_node.py
gradient_sdk/utils.py
gradient_sdk-0.0.4.dist-info/LICENSE
gradient_sdk-0.0.4.dist-info/METADATA
gradient_sdk-0.0.4.dist-info/WHEEL
gradient_sdk-0.0.4.dist-info/top_level.txt
gradient_sdk-0.0.4.dist-info/RECORD
