Metadata-Version: 2.1
Name: gradient-sdk
Version: 0.0.4
Summary: Gradient ML SDK
Home-page: https://github.com/Paperspace/gradient-sdk
Author: Paperspace Co.
Author-email: info@paperspace.com
License: UNKNOWN
Keywords: gradient sdk ml
Platform: UNKNOWN
Classifier: Development Status :: 3 - Alpha
Classifier: Intended Audience :: Developers
Classifier: Topic :: Software Development :: Libraries
Classifier: License :: OSI Approved :: MIT License
Classifier: Programming Language :: Python :: 3.5
Classifier: Programming Language :: Python :: 3.6
Classifier: Programming Language :: Python :: 3.7
Requires-Dist: wheel
Requires-Dist: hyperopt (<0.2)
Requires-Dist: pymongo
Provides-Extra: dev
Requires-Dist: tox ; extra == 'dev'
